chercher_plugin_yt/__init__.py
chercher_plugin_yt-0.1.0.dist-info/licenses/LICENSE
chercher_plugin_yt-0.1.0.dist-info/METADATA
chercher_plugin_yt-0.1.0.dist-info/WHEEL
chercher_plugin_yt-0.1.0.dist-info/entry_points.txt
chercher_plugin_yt-0.1.0.dist-info/top_level.txt
chercher_plugin_yt-0.1.0.dist-info/RECORD
